plain/vendor/CHANGELOG.md
plain/vendor/README.md
plain/vendor/__init__.py
plain/vendor/cli.py
plain/vendor/deps.py
plain/vendor/entrypoints.py
plain/vendor/exceptions.py
plain_vendor-0.10.2.dist-info/METADATA
plain_vendor-0.10.2.dist-info/WHEEL
plain_vendor-0.10.2.dist-info/entry_points.txt
plain_vendor-0.10.2.dist-info/licenses/LICENSE
plain_vendor-0.10.2.dist-info/RECORD
