Metadata-Version: 2.4
Name: plain.vendor
Version: 0.10.2
Summary: Download CDN scripts and styles as vendored dependencies.
Author-email: Dave Gaeddert <dave.gaeddert@dropseed.dev>
License-Expression: BSD-3-Clause
License-File: LICENSE
Requires-Python: >=3.13
Requires-Dist: plain<1.0.0
Requires-Dist: requests>=2.0.0
Requires-Dist: tomlkit>=0.12.1
